LICENSE
MANIFEST.in
README.rst
setup.py
virtualenvcontext/__init__.py
virtualenvcontext.egg-info/PKG-INFO
virtualenvcontext.egg-info/SOURCES.txt
virtualenvcontext.egg-info/dependency_links.txt
virtualenvcontext.egg-info/entry_points.txt
virtualenvcontext.egg-info/not-zip-safe
virtualenvcontext.egg-info/requires.txt
virtualenvcontext.egg-info/top_level.txt