Metadata-Version: 1.1
Name: virtualenvcontext
Version: 0.1.4
Summary: switch virtualenvs with a python context manager
Home-page: http://github.com/ralphbean/virtualenvcontext
Author: Ralph Bean
Author-email: ralph.bean@gmail.com
License: GPLv2+
Platform: UNKNOWN
Classifier: Development Status :: 4 - Beta
Classifier: Intended Audience :: Developers
Classifier: License :: OSI Approved :: GNU General Public License (GPL)
Classifier: Programming Language :: Python
Classifier: Programming Language :: Python :: 2.5
Classifier: Programming Language :: Python :: 2.6
Classifier: Programming Language :: Python :: 2.7
Classifier: Topic :: Software Development :: Libraries
Classifier: Topic :: Utilities
